kuttyPy/REGISTERS.py
kuttyPy/__init__.py
kuttyPyGui/BMP180.py
kuttyPyGui/KuttyPyAndroidQuiz.py
kuttyPyGui/KuttyPyGUI.py
kuttyPyGui/KuttyPyIDE.py
kuttyPyGui/KuttyPyLib.py
kuttyPyGui/KuttyPyLibNano.py
kuttyPyGui/KuttyPyLibUno.py
kuttyPyGui/KuttyPyNano.py
kuttyPyGui/KuttyPyPlus.py
kuttyPyGui/KuttyPyQuizSocketio.py
kuttyPyGui/KuttyPyUno.py
kuttyPyGui/KuttyPyVisual.py
kuttyPyGui/__init__.py
kuttyPyGui/__main__.py
kuttyPyGui/constants.py
kuttyPyGui/kuttypy.py
kuttyPyGui/listen_tcp.py
kuttyPyGui/send_udp.py
kuttyPyGui/examples/__init__.py
kuttyPyGui/examples/adc-read-direct.c
kuttyPyGui/examples/adc-read.c
kuttyPyGui/examples/blink-2.c
kuttyPyGui/examples/blink.c
kuttyPyGui/examples/copy-bit-2.c
kuttyPyGui/examples/copy-bit.c
kuttyPyGui/examples/copy.c
kuttyPyGui/examples/cro.c
kuttyPyGui/examples/echo-direct.c
kuttyPyGui/examples/echo.c
kuttyPyGui/examples/freq-counter.c
kuttyPyGui/examples/kp.h
kuttyPyGui/examples/libkp.a
kuttyPyGui/examples/pwm-tc0-direct.c
kuttyPyGui/examples/pwm-tc0.c
kuttyPyGui/examples/pwm-tc1.c
kuttyPyGui/examples/pwm-tc2-direct.c
kuttyPyGui/examples/sq-tc0.c
kuttyPyGui/examples/sq-tc1.c
kuttyPyGui/examples/sq-tc2.c
kuttyPyGui/examples/test-lcd.c
kuttyPyGui/examples/test-uart.c
kuttyPyGui/examples/voltmeter.c
kuttyPyGui/examples/x.c
kuttyPyGui/examples/ASM/adcread.S
kuttyPyGui/examples/ASM/add-2
kuttyPyGui/examples/ASM/add-2.S
kuttyPyGui/examples/ASM/add-2.hex
kuttyPyGui/examples/ASM/add-2.lst
kuttyPyGui/examples/ASM/add-2.map
kuttyPyGui/examples/ASM/add.s
kuttyPyGui/examples/ASM/and.s
kuttyPyGui/examples/ASM/blink.S
kuttyPyGui/examples/ASM/carry.S
kuttyPyGui/examples/ASM/data-direct-var.S
kuttyPyGui/examples/ASM/data-direct.S
kuttyPyGui/examples/ASM/data-immed.s
kuttyPyGui/examples/ASM/data-indirect.S
kuttyPyGui/examples/ASM/global-init.S
kuttyPyGui/examples/ASM/interrupt.S
kuttyPyGui/examples/ASM/io-direct.S
kuttyPyGui/examples/ASM/jump.S
kuttyPyGui/examples/ASM/ramp-on-R2RDAC.S
kuttyPyGui/examples/ASM/sine-wave.S
kuttyPy-2.0.8.dist-info/LICENSE
kuttyPy-2.0.8.dist-info/METADATA
kuttyPy-2.0.8.dist-info/WHEEL
kuttyPy-2.0.8.dist-info/entry_points.txt
kuttyPy-2.0.8.dist-info/top_level.txt
kuttyPy-2.0.8.dist-info/RECORD
