Metadata-Version: 2.1
Name: kuttyPy
Version: 2.0.8
Summary: Python package for KuttyPy and KuttyPyPlus AVR trainer
Home-page: https://github.com/csparkresearch/kuttypyplus
Author: Jithin B.P
Author-email: jithinbp@gmail.com
License: UNKNOWN
Project-URL: Source, https://github.com/csparkresearch/kuttypy-gui
Project-URL: Read The Docs, https://kuttypy.readthedocs.io
Project-URL: Buy Hardware, https://csparkresearch.in/kuttypy
Keywords: atmega32 trainer data-acquisition
Platform: UNKNOWN
Classifier: Development Status :: 5 - Production/Stable
Classifier: Intended Audience :: Education
Classifier: Programming Language :: Python :: 3
Classifier: License :: OSI Approved :: MIT License
Classifier: Operating System :: OS Independent
Requires-Python: >=3
License-File: LICENSE
Requires-Dist: flask
Requires-Dist: flask-cors
Requires-Dist: numpy
Requires-Dist: pyqt5
Requires-Dist: pyqtgraph
Requires-Dist: pyserial
Requires-Dist: qtconsole
Requires-Dist: scipy
Requires-Dist: werkzeug
